lionheart/__init__.py
lionheart/cli.py
lionheart/commands/collect_samples.py
lionheart/commands/cross_validate.py
lionheart/commands/customize_thresholds.py
lionheart/commands/evaluate_univariates.py
lionheart/commands/extract_features.py
lionheart/commands/guides.py
lionheart/commands/predict.py
lionheart/commands/train_model.py
lionheart/commands/validate.py
lionheart/features/__init__.py
lionheart/features/correction/__init__.py
lionheart/features/correction/correction.py
lionheart/features/correction/insert_size.py
lionheart/features/correction/normalize_megabins.py
lionheart/features/correction/poisson.py
lionheart/features/create_dataset_inference.py
lionheart/features/running_pearson_r.py
lionheart/features/running_stats.py
lionheart/modeling/__init__.py
lionheart/modeling/feature_contribution.py
lionheart/modeling/model_dict.py
lionheart/modeling/prepare_modeling.py
lionheart/modeling/prepare_modeling_command.py
lionheart/modeling/read_meta_data.py
lionheart/modeling/run_cross_validate.py
lionheart/modeling/run_customize_thresholds.py
lionheart/modeling/run_full_modeling.py
lionheart/modeling/run_predict_single_model.py
lionheart/modeling/run_univariate_analyses.py
lionheart/modeling/transformers.py
lionheart/plotting/__init__.py
lionheart/plotting/plot_inner_scores.py
lionheart/utils/__init__.py
lionheart/utils/bam_utils.py
lionheart/utils/bed_ops.py
lionheart/utils/cli_utils.py
lionheart/utils/dual_log.py
lionheart/utils/gc_content.py
lionheart/utils/global_vars.py
lionheart/utils/sparse_ops.py
lionheart/utils/subprocess.py
lionheart/utils/utils.py
lionheart-2.1.0.dist-info/LICENSE
lionheart-2.1.0.dist-info/METADATA
lionheart-2.1.0.dist-info/WHEEL
lionheart-2.1.0.dist-info/entry_points.txt
lionheart-2.1.0.dist-info/RECORD
