Metadata-Version: 2.3
Name: lionheart
Version: 2.1.0
Summary: LIONHEART is a method for detecting cancer from whole genome sequenced plasma cell-free DNA. Check the README for additional installation steps.
Keywords: cancer detection,cancer,cell-free DNA,cfDNA,fragmentomics,nucleosomics,bioinformatics
Author: Ludvig
Author-email: <mail@ludvigolsen.dk>
Requires-Python: >=3.9,<4.0
Classifier: Programming Language :: Python :: 3
Classifier: Programming Language :: Python :: 3.9
Classifier: Programming Language :: Python :: 3.10
Classifier: Programming Language :: Python :: 3.11
Classifier: Programming Language :: Python :: 3.12
Classifier: Programming Language :: Python :: 3.13
Requires-Dist: generalize (>=0.3.0,<0.4.0)
Requires-Dist: joblib (==1.4.2)
Requires-Dist: matplotlib (>=3.9.1,<4.0.0)
Requires-Dist: nattrs (>=0.2.2,<0.3.0)
Requires-Dist: numpy (==1.26.4)
Requires-Dist: packaging (>=24.1,<25.0)
Requires-Dist: pandas (==1.5.3)
Requires-Dist: rich (>=13.7.1,<14.0.0)
Requires-Dist: rich-argparse (>=1.5.2,<2.0.0)
Requires-Dist: scikit-learn (==1.0.2)
Requires-Dist: scipy (>=1.7.3,<2.0.0)
Requires-Dist: seaborn (>=0.13.2,<0.14.0)
Requires-Dist: statsmodels (==0.14.1)
Requires-Dist: utipy (>=1.0.5,<2.0.0)
Project-URL: Changelog, https://github.com/BesenbacherLab/lionheart/blob/main/CHANGELOG.md
Project-URL: Issues, https://github.com/BesenbacherLab/lionheart/issues
Project-URL: Repository, https://github.com/BesenbacherLab/lionheart
Project-URL: Resources, https://zenodo.org/records/14215762
